{
  "testResults": [
    {
      "id": "6054",
      "userId": "testUser999",
      "nickname": "testUser999",
      "result": "ESTJ",
      "answers": [
        "예",
        "예"
      ],
      "description": "체계적이고 효율적이며, 목표 달성에 집중합니다.",
      "date": "2024-09-09T23:49:52.498Z",
      "visibility": false
    },
    {
      "id": "54cf",
      "userId": "testUser999",
      "nickname": "김 흐린눈",
      "result": "INTJ",
      "answers": [
        "아니오",
        "아니오"
      ],
      "description": "독립적이고 전략적이며, 높은 목표를 설정하고 달성하는 데 집중합니다.",
      "date": "2024-09-09T23:50:11.199Z",
      "visibility": true
    },
    {
      "id": "3d1e",
      "userId": "testUser999",
      "nickname": "김 흐린눈",
      "result": "ISTJ",
      "answers": [
        "아니오",
        "예"
      ],
      "description": "책임감 있고 신뢰할 수 있으며, 전통적이고 실용적인 사고방식을 가지고 있습니다.",
      "date": "2024-09-09T23:57:44.686Z",
      "visibility": true
    },
    {
      "id": "319b",
      "userId": "mutate1234",
      "nickname": "mutate1234",
      "result": "ISTJ",
      "answers": [
        "아니오",
        "예"
      ],
      "description": "책임감 있고 신뢰할 수 있으며, 전통적이고 실용적인 사고방식을 가지고 있습니다.",
      "date": "2024-09-10T00:01:13.632Z",
      "visibility": false
    },
    {
      "id": "2993",
      "userId": "mutate1234",
      "nickname": "mutate1234",
      "result": "ESTJ",
      "answers": [
        "예",
        "예"
      ],
      "description": "체계적이고 효율적이며, 목표 달성에 집중합니다.",
      "date": "2024-09-10T00:03:01.533Z",
      "visibility": true
    },
    {
      "id": "b58a",
      "userId": "mutate1234",
      "nickname": "mutate1234",
      "result": "ESTJ",
      "answers": [
        "예",
        "예"
      ],
      "description": "체계적이고 효율적이며, 목표 달성에 집중합니다.",
      "date": "2024-09-10T00:04:09.609Z",
      "visibility": true
    },
    {
      "id": "5066",
      "userId": "mutate1234",
      "nickname": "mutate1234",
      "result": "ESTJ",
      "answers": [
        "예",
        "예"
      ],
      "description": "체계적이고 효율적이며, 목표 달성에 집중합니다.",
      "date": "2024-09-10T00:06:17.936Z",
      "visibility": false
    },
    {
      "id": "bb9e",
      "userId": "mutate1234",
      "nickname": "mutate1234",
      "result": "ISTJ",
      "answers": [
        "아니오",
        "예"
      ],
      "description": "책임감 있고 신뢰할 수 있으며, 전통적이고 실용적인 사고방식을 가지고 있습니다.",
      "date": "2024-09-10T00:09:14.967Z",
      "visibility": false
    },
    {
      "id": "08b7",
      "userId": "mutate1234",
      "nickname": "mutate1234",
      "result": "ESTJ",
      "answers": [
        "예",
        "예"
      ],
      "description": "체계적이고 효율적이며, 목표 달성에 집중합니다.",
      "date": "2024-09-10T00:10:54.978Z",
      "visibility": false
    },
    {
      "id": "9805",
      "userId": "mutate1234",
      "nickname": "mutate1234",
      "result": "ESTJ",
      "answers": [
        "예",
        "예"
      ],
      "description": "체계적이고 효율적이며, 목표 달성에 집중합니다.",
      "date": "2024-09-10T00:12:15.651Z",
      "visibility": true
    },
    {
      "id": "dd28",
      "userId": "mutate1234",
      "nickname": "mutate1234",
      "result": "ESTJ",
      "answers": [
        "예",
        "예"
      ],
      "description": "ESTJ 유형은 체계적이고 효율적인 성향을 지닌 사람들로, 목표 달성에 매우 집중합니다. 이들은 조직적이고 규율을 중시하며, 타인을 이끌고 관리하는 데 능숙합니다. 현실적이고 실용적인 접근 방식을 통해 문제를 해결하며, 사회적 책임과 규범을 중요시하는 경향이 있습니다.",
      "date": "2024-09-10T00:26:22.380Z",
      "visibility": true
    },
    {
      "id": "3909",
      "userId": "mutate1234",
      "nickname": "mutate1234",
      "result": "ESTJ",
      "answers": [
        "예",
        "예"
      ],
      "description": "ESTJ 유형은 체계적이고 효율적인 성향을 지닌 사람들로, 목표 달성에 매우 집중합니다. 이들은 조직적이고 규율을 중시하며, 타인을 이끌고 관리하는 데 능숙합니다. 현실적이고 실용적인 접근 방식을 통해 문제를 해결하며, 사회적 책임과 규범을 중요시하는 경향이 있습니다.",
      "date": "2024-09-10T00:28:18.241Z",
      "visibility": true
    },
    {
      "id": "d175",
      "userId": "mutate1234",
      "nickname": "mutate1234",
      "result": "ESTJ",
      "answers": [
        "예",
        "예"
      ],
      "description": "ESTJ 유형은 체계적이고 효율적인 성향을 지닌 사람들로, 목표 달성에 매우 집중합니다. 이들은 조직적이고 규율을 중시하며, 타인을 이끌고 관리하는 데 능숙합니다. 현실적이고 실용적인 접근 방식을 통해 문제를 해결하며, 사회적 책임과 규범을 중요시하는 경향이 있습니다.",
      "date": "2024-09-10T00:29:55.804Z",
      "visibility": true
    },
    {
      "id": "e713",
      "userId": "mutate1234",
      "nickname": "mutate1234",
      "result": "ESTJ",
      "answers": [
        "예",
        "예"
      ],
      "description": "ESTJ 유형은 체계적이고 효율적인 성향을 지닌 사람들로, 목표 달성에 매우 집중합니다. 이들은 조직적이고 규율을 중시하며, 타인을 이끌고 관리하는 데 능숙합니다. 현실적이고 실용적인 접근 방식을 통해 문제를 해결하며, 사회적 책임과 규범을 중요시하는 경향이 있습니다.",
      "date": "2024-09-10T00:30:35.983Z",
      "visibility": true
    },
    {
      "id": "265a",
      "userId": "mutate1234",
      "nickname": "mutate1234",
      "result": "ESTJ",
      "answers": [
        "예",
        "예"
      ],
      "description": "ESTJ 유형은 체계적이고 효율적인 성향을 지닌 사람들로, 목표 달성에 매우 집중합니다. 이들은 조직적이고 규율을 중시하며, 타인을 이끌고 관리하는 데 능숙합니다. 현실적이고 실용적인 접근 방식을 통해 문제를 해결하며, 사회적 책임과 규범을 중요시하는 경향이 있습니다.",
      "date": "2024-09-10T00:30:51.989Z",
      "visibility": true
    },
    {
      "id": "1894",
      "userId": "mutate1234",
      "nickname": "mutate1234",
      "result": "ESTJ",
      "answers": [
        "예",
        "예"
      ],
      "description": "ESTJ 유형은 체계적이고 효율적인 성향을 지닌 사람들로, 목표 달성에 매우 집중합니다. 이들은 조직적이고 규율을 중시하며, 타인을 이끌고 관리하는 데 능숙합니다. 현실적이고 실용적인 접근 방식을 통해 문제를 해결하며, 사회적 책임과 규범을 중요시하는 경향이 있습니다.",
      "date": "2024-09-10T00:33:23.199Z",
      "visibility": true
    },
    {
      "id": "01cc",
      "userId": "tester997777",
      "nickname": "강구",
      "result": "INTJ",
      "answers": [
        null,
        null
      ],
      "description": "INTJ 유형은 독립적이고 전략적인 사고를 지닌 사람들로, 논리적이고 분석적으로 문제를 해결합니다. 이들은 높은 목표를 설정하고 이를 달성하기 위해 체계적이고 효율적으로 계획을 세우며, 장기적인 시각으로 미래를 바라보는 경향이 있습니다. 목표 달성에 집중하며, 타인과의 관계보다는 성취와 결과를 중시하는 성향이 강합니다.",
      "date": "2024-09-10T01:02:31.704Z",
      "visibility": true
    },
    {
      "id": "5a2e",
      "userId": "mutate1234",
      "nickname": "쇼",
      "result": "ESTJ",
      "answers": [
        "예",
        "예",
        "아니오",
        "아니오",
        "아니오",
        "아니오",
        "아니오",
        "예",
        "예",
        "예",
        "예",
        "예",
        "예",
        "예",
        "예",
        "예",
        "예",
        "예",
        "예",
        "예"
      ],
      "description": "ESTJ 유형은 체계적이고 효율적인 성향을 지닌 사람들로, 목표 달성에 매우 집중합니다. 이들은 조직적이고 규율을 중시하며, 타인을 이끌고 관리하는 데 능숙합니다. 현실적이고 실용적인 접근 방식을 통해 문제를 해결하며, 사회적 책임과 규범을 중요시하는 경향이 있습니다.",
      "date": "2024-09-10T11:58:30.920Z",
      "visibility": true
    },
    {
      "id": "d0d5",
      "userId": "testa1234",
      "nickname": "rr",
      "result": "INFP",
      "answers": [
        "예",
        null,
        null,
        null,
        null,
        null,
        null,
        null,
        null,
        null,
        null,
        null,
        null,
        null,
        null,
        null,
        null,
        null,
        null,
        null
      ],
      "description": "INFP 유형은 이상적이고 창의적인 성향을 지닌 사람들로, 내면의 가치와 신념을 중요하게 생각합니다. 이들은 타인의 감정에 공감하고, 세상에 긍정적인 변화를 가져오고자 하는 강한 열망을 가지고 있습니다. 창의적이고 상상력이 풍부하며, 예술적 표현이나 글쓰기를 통해 자신의 생각을 전달하는 것을 좋아합니다.",
      "date": "2024-09-10T12:16:31.815Z",
      "visibility": true
    }
  ]
}